pepperize_cdk_organizations/__init__.py
pepperize_cdk_organizations/py.typed
pepperize_cdk_organizations/_jsii/__init__.py
pepperize_cdk_organizations/_jsii/cdk-organizations@0.7.985.jsii.tgz
pepperize.cdk_organizations-0.7.985.dist-info/LICENSE
pepperize.cdk_organizations-0.7.985.dist-info/METADATA
pepperize.cdk_organizations-0.7.985.dist-info/WHEEL
pepperize.cdk_organizations-0.7.985.dist-info/top_level.txt
pepperize.cdk_organizations-0.7.985.dist-info/RECORD
