Metadata-Version: 2.1
Name: pepperize.cdk-organizations
Version: 0.7.985
Summary: Manage AWS organizations, organizational units (OU), accounts and service control policies (SCP).
Home-page: https://github.com/pepperize/cdk-organizations.git
Author: Patrick Florek<patrick.florek@gmail.com>
License: MIT
Project-URL: Source, https://github.com/pepperize/cdk-organizations.git
Classifier: Intended Audience :: Developers
Classifier: Operating System :: OS Independent
Classifier: Programming Language :: JavaScript
Classifier: Programming Language :: Python :: 3 :: Only
Classifier: Programming Language :: Python :: 3.8
Classifier: Programming Language :: Python :: 3.9
Classifier: Programming Language :: Python :: 3.10
Classifier: Programming Language :: Python :: 3.11
Classifier: Typing :: Typed
Classifier: Development Status :: 5 - Production/Stable
Classifier: License :: OSI Approved
Requires-Python: ~=3.8
License-File: LICENSE
Requires-Dist: aws-cdk-lib<3.0.0,>=2.37.1
Requires-Dist: constructs<11.0.0,>=10.0.5
Requires-Dist: jsii<2.0.0,>=1.106.0
Requires-Dist: publication>=0.0.3
Requires-Dist: typeguard<4.3.0,>=2.13.3
